<?xml version="1.0"?>
<config xmlns:xsi="http://www.w3.org/2001/XMLSchema-instance"
        xsi:noNamespaceSchemaLocation="urn:magento:module:Magento_Backend:etc/menu.xsd">
    <menu>
        <!--
            Shared top-level eTechFlow sidebar entry.

            Declared identically by EVERY eTechFlow module — Magento merges
            entries with the same id, so the entry exists exactly once even
            with all modules installed, and missing exactly when zero are.
            Hovering it opens a mega-menu where each module contributes one
            column (or a single link if the module has only one page).

            sortOrder 88 clusters us with the established vendor extensions
            (Amasty, Magefan typically sit around 85–89) just above Magento's
            Stores entry. Going higher (e.g. 305) parks us at the very bottom
            of the sidebar under "Find Partners & Extensions", which is where
            Hyva-admin's auto-grown items end up.
        -->
        <add id="eTechFlow::root"
             title="eTechFlow"
             module="ETechFlow_InStorePickup"
             sortOrder="88"
             resource="Magento_Backend::admin"/>

        <add id="ETechFlow_InStorePickup::isp_root"
             title="In-Store Pickup"
             module="ETechFlow_InStorePickup"
             sortOrder="10"
             parent="eTechFlow::root"
             resource="ETechFlow_InStorePickup::menu"/>

        <add id="ETechFlow_InStorePickup::stores"
             title="Stores"
             module="ETechFlow_InStorePickup"
             sortOrder="10"
             parent="ETechFlow_InStorePickup::isp_root"
             action="etechflow_isp/store/index"
             resource="ETechFlow_InStorePickup::stores"/>

        <add id="ETechFlow_InStorePickup::holidays"
             title="Holidays"
             module="ETechFlow_InStorePickup"
             sortOrder="20"
             parent="ETechFlow_InStorePickup::isp_root"
             action="etechflow_isp/holiday/index"
             resource="ETechFlow_InStorePickup::holidays"/>

        <add id="ETechFlow_InStorePickup::tags"
             title="Store Tags"
             module="ETechFlow_InStorePickup"
             sortOrder="30"
             parent="ETechFlow_InStorePickup::isp_root"
             action="etechflow_isp/tag/index"
             resource="ETechFlow_InStorePickup::tags"/>

        <add id="ETechFlow_InStorePickup::amenities"
             title="Amenities"
             module="ETechFlow_InStorePickup"
             sortOrder="40"
             parent="ETechFlow_InStorePickup::isp_root"
             action="etechflow_isp/amenity/index"
             resource="ETechFlow_InStorePickup::amenities"/>

        <add id="ETechFlow_InStorePickup::pickup_windows"
             title="Pickup Windows"
             module="ETechFlow_InStorePickup"
             sortOrder="50"
             parent="ETechFlow_InStorePickup::isp_root"
             action="etechflow_isp/pickupwindow/index"
             resource="ETechFlow_InStorePickup::pickup_windows"/>

        <!--
            Shared "Settings" column header in the eTechFlow mega-menu.

            Declared identically by every eTechFlow module so it merges to
            one column. The Configuration leaf (below) lives inside it so
            it gets a proper column home in the mega-menu — orphan leaves
            siblings of column-header parents dangle awkwardly at the
            bottom of the panel.
        -->
        <add id="eTechFlow::settings"
             title="Settings"
             module="ETechFlow_InStorePickup"
             sortOrder="500"
             parent="eTechFlow::root"
             resource="Magento_Backend::admin"/>

        <!--
            Shared "Configuration" leaf inside the Settings column.
            All eTechFlow modules declare this same id with their own
            section URL — Magento merges so only one entry appears, and
            clicking it opens Stores → Configuration with the eTechFlow
            tab pre-expanded. Any module's section URL works because
            they all live under <tab id="etechflow">.
        -->
        <add id="eTechFlow::configuration"
             title="Configuration"
             module="ETechFlow_InStorePickup"
             sortOrder="10"
             parent="eTechFlow::settings"
             action="adminhtml/system_config/edit/section/etechflow_instorepickup"
             resource="Magento_Config::config"/>
    </menu>
</config>
